OpenFrpLib/Account.py
OpenFrpLib/NetworkController.py
OpenFrpLib/Proxies.py
OpenFrpLib/__init__.py
OpenFrpLib-1.4.0.dist-info/LICENSE
OpenFrpLib-1.4.0.dist-info/METADATA
OpenFrpLib-1.4.0.dist-info/WHEEL
OpenFrpLib-1.4.0.dist-info/top_level.txt
OpenFrpLib-1.4.0.dist-info/RECORD
