Metadata-Version: 2.1
Name: OpenFrpLib
Version: 1.4.0
Summary: UNKNOWN
Home-page: https://github.com/LxHTT/OpenFrpLib
Author: LxHTT
Author-email: lxhtt@vip.qq.com
License: MIT
Project-URL: Documentation, https://github.com/LxHTT/OpenFrpLib/blob/master/README.md
Project-URL: Source Code, https://github.com/LxHTT/OpenFrpLib
Project-URL: Bug Tracker, https://github.com/LxHTT/OpenFrpLib/issues
Platform: UNKNOWN
Classifier: Programming Language :: Python :: 3.8
Classifier: License :: OSI Approved :: MIT License
Classifier: Operating System :: OS Independent
Requires-Python: >=3.7, <=3.10
Requires-Dist: requests>=2.31.0
Requires-Dist: pynacl>=1.5.0
